Workbook

Sheet Summary
A1: Aileron + Elevon Servo Selection Summary
A2: Prepared for the 12S VTOL electronics configuration. Prices are approximate and must be re-checked before purchase.
A3: Design assumption | B3: Value | C3: Implication
A4: Battery architecture | B4: 2×6S in series = 12S, 44.4 V nominal / 50.4 V full | C4: Servos must be powered from a regulated 6–8.4 V BEC, not raw 12S.
A5: Flight controller in BOM | B5: MATEKSYS F405-HDTE | C5: Can command PWM servos; do not use FC/PDB small regulator as the main high-current servo rail.
A6: PDB in BOM | B6: MATEKSYS FCHUB-12S | C6: Good for 12S distribution, but it does not provide an 8.4 V high-current servo rail.
A7: Aileron required design torque | B7: 4.195 Nm = 42.8 kg·cm | C7: Direct drive requires a non-slim high-torque servo; slim servo needs mechanical advantage.
A8: Elevon required design torque | B8: 4.781 Nm = 48.8 kg·cm | C8: This is the sizing driver; choose linkage around 2.7:1 to 3.0:1 if using 20 kg·cm slim servos.
A9: Recommended servo | B9: KST A15-1810 V8.0 | C9: Best slim/low-profile balance: 20 kg·cm @ 8.4 V, 15 mm thickness, 42 g.
A10: Recommended linkage | B10: 10 mm servo-arm radius + 27–30 mm surface horn | C10: 2.7:1 to 3.0:1 ratio. 3.0:1 gives 60 kg·cm effective torque but requires about 60° servo travel for 20° surface deflection.
A11: Recommended servo power | B11: Hobbywing UBEC 25A HV set to 8.4 V | C11: Use for four high-torque HV servos. 10A HV UBEC is acceptable only for 1–2 servos or very light duty.
A12: Final design note | B12: Bench-test before flight | C12: Check servo current, temperature, linkage stiffness, backlash, flutter, and actual max airspeed.

Sheet Load_Basis
A1: Load Basis From Uploaded Calculations
A2: Torque values already include safety factor and direct-drive efficiency from the uploaded calculations.
A4: Surface | B4: Area [m²] | C4: Design speed [m/s] | D4: 20° conservative force [N] | E4: Hinge moment [Nm] | F4: Design torque [Nm] | G4: Design torque [kg·cm] | H4: Practical pin recommendation | I4: Source
A5: Aileron | B5: 0.05676 | C5: 24 | D5: 41.95 | E5: 1.258 | F5: 4.195 | G5: =F5*10.19716213 -> 42.777095 | H5: 6 mm × 30 mm minimum; 8 mm better if space allows | I5: Uploaded aileron_direct_drive_pin_calculation.pdf
A6: Elevon | B6: 0.049 | C6: 24 | D6: 36.22 | E6: 1.434 | F6: 4.781 | G6: =F6*10.19716213 -> 48.752632 | H6: 7 mm × 30 mm minimum; 8 mm preferred | I6: Uploaded elevon_direct_drive_pin_calculation.pdf

Sheet Servo_Options
A1: Servo Options for Aileron and Elevon
A2: Min linkage ratio is calculated against the aileron and elevon design torques. Effective torque assumes no additional losses beyond the uploaded torque margin.
A4: Rank | B4: Servo | C4: Price approx. | D4: Voltage | E4: Torque @ HV [kg·cm] | F4: Speed @ HV [s/60°] | G4: Dimensions L×W×H [mm] | H4: Thickness [mm] | I4: Weight [g] | J4: Motor/gears | K4: Spline | L4: Aileron min ratio | M4: Elevon min ratio | N4: Eff. torque @2.5:1 | O4: Eff. torque @2.7:1 | P4: Eff. torque @3.0:1 | Q4: Direct-drive fit? | R4: Recommended use | S4: Source URL
A5: 1 | B5: KST A15-1810 V8.0 | C5: €89.90 / $79.99 | D5: 6.0–8.4 V | E5: 20 | F5: 0.1 | G5: 35.5×15×32.5 | H5: 15 | I5: 42 | J5: Coreless, hardened steel | K5: 25T-6 | L5: =Load_Basis!$G$5/E5 -> 2.1388548 | M5: =Load_Basis!$G$6/E5 -> 2.4376316 | N5: =E5*2.5 -> 50 | O5: =E5*2.7 -> 54 | P5: =E5*3 -> 60 | Q5: No | R5: Primary recommendation: aileron + elevon with 2.7:1–3.0:1 linkage | S5: https://www.kst-servo-shop.de/KST-A15-1810-V8.0-20kg.cmat8.4V-Coreless-Motor/KST-1026
A6: 2 | B6: AGFRC A50BHL | C6: $45.99 | D6: 4.8–8.4 V | E6: 19 | F6: 0.073 | G6: 40.8×20.2×26.5 | H6: 20.2 | I6: 50 | J6: Brushless, steel | K6: 25T Ø5.92 | L6: =Load_Basis!$G$5/E6 -> 2.2514261 | M6: =Load_Basis!$G$6/E6 -> 2.565928 | N6: =E6*2.5 -> 47.5 | O6: =E6*2.7 -> 51.3 | P6: =E6*3 -> 57 | Q6: No | R6: Budget alternative; more RC-car oriented, thicker than KST | S6: https://www.agfrc.com/index.php?id=2436
A7: 3 | B7: XQ Power XQ-BLS325 | C7: €62.95 | D7: 6.0–8.4 V | E7: 25 | F7: 0.08 | G7: 41×20.5×28 | H7: 20.5 | I7: 60 | J7: Brushless, steel | K7: 25T | L7: =Load_Basis!$G$5/E7 -> 1.7110838 | M7: =Load_Basis!$G$6/E7 -> 1.9501053 | N7: =E7*2.5 -> 62.5 | O7: =E7*2.7 -> 67.5 | P7: =E7*3 -> 75 | Q7: No | R7: Higher torque low-profile option; verify quality before flight | S7: https://www.rovansports.nl/de/xq-power-xq-bls325-hv-brushless-low-profile-servo.html
A8: 4 | B8: MKS HV747 | C8: $109.45 | D8: 6.0–8.4 V | E8: 15 | F8: 0.13 | G8: 35.5×15×28.5 | H8: 15 | I8: 38.55 | J8: Coreless, metal | K8: MKS 25T class | L8: =Load_Basis!$G$5/E8 -> 2.8518063 | M8: =Load_Basis!$G$6/E8 -> 3.2501755 | N8: =E8*2.5 -> 37.5 | O8: =E8*2.7 -> 40.5 | P8: =E8*3 -> 45 | Q8: No | R8: High quality but needs high linkage ratio; not ideal for 20° elevon | S8: https://mks-servo.com/HV747
A9: 5 | B9: KST X15-1208 V8.0 | C9: €82.90 | D9: 6.0–8.4 V | E9: 13.5 | F9: 0.07 | G9: 35.5×15×32.5 | H9: 15 | I9: 40 | J9: Coreless, hardened steel | K9: 25T-6 | L9: =Load_Basis!$G$5/E9 -> 3.1686737 | M9: =Load_Basis!$G$6/E9 -> 3.6113061 | N9: =E9*2.5 -> 33.75 | O9: =E9*2.7 -> 36.45 | P9: =E9*3 -> 40.5 | Q9: No | R9: Fast 15 mm servo; torque too low for this load unless high ratio | S9: https://kstservos.com/products/x15-1208-cyclic-coreless-hv-digital-servo-motor
A10: 6 | B10: MKS HV6150H | C10: $71.11 / €65 class | D10: 4.8–8.4 V | E10: 10.9 | F10: 0.159 | G10: 23.5×11×25 | H10: 11 | I10: 16.4 | J10: Coreless, metal alloy | K10: MKS micro | L10: =Load_Basis!$G$5/E10 -> 3.9245041 | M10: =Load_Basis!$G$6/E10 -> 4.4727185 | N10: =E10*2.5 -> 27.25 | O10: =E10*2.7 -> 29.43 | P10: =E10*3 -> 32.7 | Q10: No | R10: Too weak for main aileron/elevon load; only for smaller surfaces | S10: https://www.mks-servo.com/HV6150H
A11: 7 | B11: Savox SV-1270TG+ | C11: €78–90 | D11: 6.0–8.4 V | E11: 45 | F11: 0.1 | G11: 40.3×20.2×37.2 | H11: 20.2 | I11: 64 | J11: Coreless, titanium | K11: 25T | L11: =Load_Basis!$G$5/E11 -> 0.95060211 | M11: =Load_Basis!$G$6/E11 -> 1.0833918 | N11: =E11*2.5 -> 112.5 | O11: =E11*2.7 -> 121.5 | P11: =E11*3 -> 135 | Q11: Borderline/No for elevon | R11: Not slim; direct-drive aileron possible, elevon still needs margin | S11: https://www.teamsavox.com/product/sv-1270tgp/

Sheet Linkage_Setup
A1: Recommended Linkage Geometry
A2: Ratios assume surface torque = servo stall torque × surface horn radius / servo arm radius. Servo travel is surface deflection × ratio.
A4: Setup | B4: Servo model | C4: Servo torque [kg·cm] | D4: Servo arm radius [mm] | E4: Surface horn radius [mm] | F4: Linkage ratio | G4: Effective surface torque [kg·cm] | H4: Aileron margin | I4: Elevon margin | J4: Servo travel for 20° surface | K4: Assessment | L4: Notes
A5: Strict default travel | B5: KST A15-1810 | C5: 20 | D5: 10 | E5: 25 | F5: =E5/D5 -> 2.5 | G5: =C5*F5 -> 50 | H5: =G5/Load_Basis!$G$5-1 -> 0.16884982 | I5: =G5/Load_Basis!$G$6-1 -> 0.025585652 | J5: =20*F5 -> 50 | K5: Acceptable but tight for elevon | L5: Fits ±50° default travel; verify load with ground test.
A6: Recommended compromise | B6: KST A15-1810 | C6: 20 | D6: 10 | E6: 27 | F6: =E6/D6 -> 2.7 | G6: =C6*F6 -> 54 | H6: =G6/Load_Basis!$G$5-1 -> 0.26235781 | I6: =G6/Load_Basis!$G$6-1 -> 0.1076325 | J6: =20*F6 -> 54 | K6: Best starting point | L6: Requires about 54° servo travel for 20° surface; program endpoints or limit surface to about 18.5° if needed.
A7: High margin | B7: KST A15-1810 | C7: 20 | D7: 10 | E7: 30 | F7: =E7/D7 -> 3 | G7: =C7*F7 -> 60 | H7: =G7/Load_Basis!$G$5-1 -> 0.40261979 | I7: =G7/Load_Basis!$G$6-1 -> 0.23070278 | J7: =20*F7 -> 60 | K7: Strongest torque margin | L7: Requires about 60° servo travel for 20° surface. Use only if servo travel and linkage geometry allow it.
A8: Budget similar | B8: AGFRC A50BHL | C8: 19 | D8: 10 | E8: 27 | F8: =E8/D8 -> 2.7 | G8: =C8*F8 -> 51.3 | H8: =G8/Load_Basis!$G$5-1 -> 0.19923992 | I8: =G8/Load_Basis!$G$6-1 -> 0.052250878 | J8: =20*F8 -> 54 | K8: Possible budget option | L8: Thicker than KST; more RC-car oriented. Test centering, heat, and backlash.
A9: Higher-torque low profile | B9: XQ Power XQ-BLS325 | C9: 25 | D9: 10 | E9: 20 | F9: =E9/D9 -> 2 | G9: =C9*F9 -> 50 | H9: =G9/Load_Basis!$G$5-1 -> 0.16884982 | I9: =G9/Load_Basis!$G$6-1 -> 0.025585652 | J9: =20*F9 -> 40 | K9: Good torque math | L9: Only 40° servo travel at 20° surface; quality/reliability must be validated.

Sheet BOM_Recommendation
A1: Recommended Servo + Linkage BOM
A2: Quantity assumes two ailerons and two elevons = four control-surface servos total.
A4: Item | B4: Qty | C4: Unit price approx. | D4: Subtotal formula | E4: Purpose | F4: Recommended spec | G4: Source URL | H4: Notes
A5: KST A15-1810 V8.0 servo | B5: 4 | C5: 89.9 | D5: =B5*C5 -> 359.6 | E5: Aileron/elevon actuation | F5: 20 kg·cm @ 8.4 V, 15 mm thickness, 42 g | G5: https://www.kst-servo-shop.de/KST-A15-1810-V8.0-20kg.cmat8.4V-Coreless-Motor/KST-1026 | H5: Primary recommendation.
A6: Hobbywing UBEC 25A HV | B6: 1 | C6: 107 | D6: =B6*C6 -> 107 | E6: Servo power rail | F6: 3–18S input, 5.2/6/7.4/8.4 V, 25A continuous / 50A peak | G6: https://www.hobbywing.com/en/products/ubec-25a-hv95.html | H6: Set to 8.4 V for HV servo torque. Price source in USD MSRP; EU price may differ.
A7: KST / 25T aluminum servo arms | B7: 4 | C7: 10.9 | D7: =B7*C7 -> 43.6 | E7: Servo-side arms | F7: 25T-6, aluminum, M3 holes; shorten/drill to 10 mm radius if needed | G7: https://www.kst-servo-shop.de/Alu-Servoarm-44-5-50-8-mm-M3-25T-6-KST-0625.50/KST-4134 | H7: Avoid plastic arms for this torque level.
A8: 30 mm control horns | B8: 4 | C8: 1.9 | D8: =B8*C8 -> 7.6 | E8: Surface-side horns | F8: 27–30 mm effective radius depending on final linkage ratio | G8: https://www.engelmt.de/mtaccessories/linking-material/control-horn/control-horns-smal-30mm | H8: Use reinforced mounting plates or bonded hardpoints.
A9: M3 ball links / hardware | B9: 1 | C9: 7.8 | D9: =B9*C9 -> 7.8 | E9: Slop-reduced link joints | F9: 10-pack M3 ball links | G9: https://www.gator-rc.com/products/secraft-ball-link-3mm-qty-10 | H9: One pack should cover 4 linkages with spares.
A10: M3 adjustable pushrods | B10: 4 | C10: 11.49 | D10: =B10*C10 -> 45.96 | E10: Pushrod linkage | F10: 2.5 mm/M3 adjustable rods, length selected in CAD | G10: https://www.rcwarehouse.nl/shop/1772511-ph2-5mm-m3-55mm-65mm-75mm-85mm-95mm-l30mm-multiple-adjustable-push-rod-rod-end-ball-joint-linkage-set-assembly-servo-connecting-rod-stainless-steel-for-rc-airplane-aircraft-boat-4396 | H10: Choose rod length after servo/horn placement is fixed.
A11: Estimated total | D11: =SUM(D5:D10) -> 571.56 | E11: Planning total | H11: Excludes shipping/VAT differences and spare parts.

Sheet BEC_Power
A1: Servo Power Options
A2: Do not power four high-torque HV servos from the FC/PDB's small 5 V regulator.
A4: BEC | B4: Price approx. | C4: Input voltage | D4: Output voltage | E4: Current rating | F4: Size/weight | G4: Use case | H4: Source URL
A5: Hobbywing UBEC 10A HV | B5: €43 / varies | C5: 3–14S LiPo | D5: 6.0 / 7.4 / 8.4 V | E5: 10A continuous / 25A peak | F5: 55×25×12 mm / 35 g | G5: Acceptable for 1–2 servos or light duty; not my pick for four control servos. | H5: https://www.hobbywing.com/en/products/ubec-10a-hv289
A6: Hobbywing UBEC 25A HV | B6: $107 MSRP / varies | C6: 3–18S LiPo | D6: 5.2 / 6.0 / 7.4 / 8.4 V | E6: 25A continuous / 50A peak | F6: 55×40.2×17.6 mm / 74 g | G6: Recommended for four HV control-surface servos. | H6: https://www.hobbywing.com/en/products/ubec-25a-hv95.html

Sheet Sources
A1: Sources and Verification Notes
A2: URLs are plain text for auditability. Re-check availability/prices before ordering.
A4: Category | B4: Item | C4: URL | D4: Data used
A5: Calculation | B5: Aileron direct-drive calculation | C5: Uploaded aileron_direct_drive_pin_calculation.pdf | D5: Aileron design torque 4.195 Nm / 42.8 kg·cm and pin sizing basis.
A6: Calculation | B6: Elevon direct-drive calculation | C6: Uploaded elevon_direct_drive_pin_calculation.pdf | D6: Elevon design torque 4.781 Nm / 48.8 kg·cm and pin sizing basis.
A7: Servo | B7: KST A15-1810 | C7: https://kstservos.com/products/a15-1810-20kg-0-10sec-hv-phosphor-bronze-hardened-steel-gear-servo | D7: 20 kg·cm @ 8.4 V, 0.10 s/60°, 35.5×15×32.5 mm, 42 g.
A8: Servo | B8: KST A15-1810 EU price | C8: https://www.kst-servo-shop.de/KST-A15-1810-V8.0-20kg.cmat8.4V-Coreless-Motor/KST-1026 | D8: €89.90 current example price.
A9: Servo | B9: AGFRC A50BHL | C9: https://www.agfrc.com/index.php?id=2436 | D9: 19 kg·cm @ 8.4 V, 0.073 s/60°, 40.8×20.2×26.5 mm, $45.99.
A10: Servo | B10: XQ Power XQ-BLS325 | C10: https://www.rovansports.nl/de/xq-power-xq-bls325-hv-brushless-low-profile-servo.html | D10: 25 kg·cm @ 8.4 V, 0.08 s/60°, 41×20.5×28 mm, €62.95.
A11: Servo | B11: MKS HV747 | C11: https://mks-servo.com/HV747 | D11: 15 kg·cm @ 8.2 V, 35.5×15×28.5 mm.
A12: Servo | B12: MKS HV6150H | C12: https://www.mks-servo.com/HV6150H | D12: 10.9 kg·cm @ 8.2 V, 23.5×11×25 mm.
A13: Servo | B13: KST X15-1208 | C13: https://kstservos.com/products/x15-1208-cyclic-coreless-hv-digital-servo-motor | D13: 13.5 kg·cm @ 8.4 V, 35.5×15×32.5 mm.
A14: BEC | B14: Hobbywing UBEC 10A HV | C14: https://www.hobbywing.com/en/products/ubec-10a-hv289 | D14: 3–14S input, 6/7.4/8.4 V output, 10A continuous / 25A peak.
A15: BEC | B15: Hobbywing UBEC 25A HV | C15: https://www.hobbywing.com/en/products/ubec-25a-hv95.html | D15: 3–18S input, 5.2/6/7.4/8.4 V output, 25A continuous / 50A peak.
... A20: Linkage | B20: Adjustable M3 pushrod set | C20: https://www.rcwarehouse.nl/shop/1772511-ph2-5mm-m3-55mm-65mm-75mm-85mm-95mm-l30mm-multiple-adjustable-push-rod-rod-end-ball-joint-linkage-set-assembly-servo-connecting-rod-stainless-steel-for-rc-airplane-aircraft-boat-4396 | D20: 2.5 mm/M3 pushrod linkage, €11.49 example.
